setup.cfg
setup.py
rada_package_moiseieiva/__init__.py
rada_package_moiseieiva/descriptors.py
rada_package_moiseieiva/rada_consoles.py
rada_package_moiseieiva/rada_databases.py
rada_package_moiseieiva/rada_factories.py
rada_package_moiseieiva/rada_metaclass.py
rada_package_moiseieiva/rada_models.py
rada_package_moiseieiva/utils.py
rada_package_moiseieiva/verh_rada.py
rada_package_moiseieiva.egg-info/PKG-INFO
rada_package_moiseieiva.egg-info/SOURCES.txt
rada_package_moiseieiva.egg-info/dependency_links.txt
rada_package_moiseieiva.egg-info/entry_points.txt
rada_package_moiseieiva.egg-info/not-zip-safe
rada_package_moiseieiva.egg-info/top_level.txt