Metadata-Version: 1.0
Name: rada-package-moiseieiva
Version: 0.0.dev0
Summary: rada project
Home-page: UNKNOWN
Author: Irina Moiseieiva
Author-email: UNKNOWN
License: UNKNOWN
Platform: UNKNOWN
